ezimage.py
ezimage-0.8.data/scripts/ezimage
ezimage-0.8.dist-info/METADATA
ezimage-0.8.dist-info/WHEEL
ezimage-0.8.dist-info/top_level.txt
ezimage-0.8.dist-info/RECORD
