Metadata-Version: 2.1
Name: ezimage
Version: 0.8
Summary: Load and display images and access its content data with one-liners. A PIL wrapper ideal for machine learning and image processing.
Home-page: https://github.com/miladiouss/ezimage
Author: Milad Pourrahmani (Miladiouss)
Author-email: miladiouss@gmail.com
License: UNKNOWN
Platform: UNKNOWN
Classifier: Programming Language :: Python :: 3
Classifier: License :: OSI Approved :: MIT License
Classifier: Operating System :: OS Independent
